<?xml version="1.0" encoding="UTF-8"?>
<objects serializationModel="Studio.02.01.00">
	<object class="AudioFile" id="{26044d27-207d-4c20-8b2d-9af72fcbd73f}">
		<property name="assetPath">
			<value>SFX/Dogs/Bark/Type1/BARK1_01.mp3</value>
		</property>
		<property name="frequencyInKHz">
			<value>44.0999985</value>
		</property>
		<property name="channelCount">
			<value>2</value>
		</property>
		<property name="length">
			<value>0.75755102040816324</value>
		</property>
		<relationship name="masterAssetFolder">
			<destination>{805f1032-8161-4daf-a23c-11b887cc2248}</destination>
		</relationship>
	</object>
</objects>
